my_sort/__init__.py
my_sort/cli.py
my_sort_prokopiv-2.2.2.dist-info/METADATA
my_sort_prokopiv-2.2.2.dist-info/WHEEL
my_sort_prokopiv-2.2.2.dist-info/entry_points.txt
my_sort_prokopiv-2.2.2.dist-info/top_level.txt
my_sort_prokopiv-2.2.2.dist-info/RECORD
