Metadata-Version: 2.4
Name: my-sort-prokopiv
Version: 2.2.2
Summary: A small implementation of Unix sort (supports -r and -n) implemented with Click
Author: Ваше Ім'я
Classifier: Programming Language :: Python :: 3
Classifier: Operating System :: OS Independent
Requires-Python: >=3.8
Requires-Dist: click>=8.0
Dynamic: author
Dynamic: classifier
Dynamic: description
Dynamic: description-content-type
Dynamic: requires-dist
Dynamic: requires-python
Dynamic: summary
